{"I5IZPKpsZ0PeFbDbZkBrxA==":"ftasteel-128x128.png","g24HzrY3nRE+e9xMPJjPfA==":"images%20(6)-2000x2497.jpg","OYiEgJ9FIiACrJvCad/Nsw==":"mbr-2000x1333.jpg","yfUzh+wNyGGtPBiDTgbsDg==":"workforce-app-field-2000x2000.jpg","AYfzNk0snV5AWwfaA1JTsQ==":"9350927_orig-2000x1594.jpg","DSSr6Hku1teRwkY1YnqdFw==":"mobile-workforce-680x365_c-2000x1073.jpg","w3QBA/kBo6wkBBTvOEq0mw==":"img-2000x1500.jpg","DH1OKYdaZdaf60ovHfJYKw==":"img-1-2000x1500.jpg","FvAukpLBI6lIt71V/BeEKQ==":"computer&map-671x386.jpg","7VnoBXyNLOjiARoJeCUTzQ==":"adobe%20spark%20(94)-2560x2560.jpg","gQy5LebovGufGcmrp/5/tg==":"nkcppv-b88337940z-620x399.jpg","gCtly/Ysn1XTtV+Wf1B3Mg==":"mbr-1-2000x1333.jpg","nSYKxpogQQjYsQnxun8HrQ==":"mbr-2-2000x1333.jpg","MJMimXuu8bCgnCy9nUZ+rA==":"mbr-2000x1334.jpg","g0oaXebEuaNk+q8Kxt+XOw==":"mbr-2000x2995.jpg","6KPdmBunsWefbexD5Ale2w==":"17758262_1492536397481012_8018865693756767061_o-2000x1333.jpg","/waBoIpTC4cQdpHhg9XEbQ==":"17758262_1492536397481012_8018865693756767061_o%20(2)-2000x1124.jpg","8rmcG1RZF05krBr/k01Y8w==":"18766742_1549554081779243_1260038484491932298_o-2000x1329.jpg","VD02cjPXggJ/1wYlB8rcHg==":"10710849_800296080038384_3152602403113904518_n-2000x740.jpg","WlEpw2wJ0JWTvcnKI4g/EQ==":"17758262_1492536397481012_8018865693756767061_o-1400x933.jpg","OErqKFatDi5MpBUoYGgHlA==":"adobe%20spark%20(4)-600x600.jpg","FCD+BIPdzUvSx9UEXBNEHA==":"adobe%20spark%20(5)-600x600.jpg","WQKUz1a3hpE3Go0VO3bkmg==":"adobe%20spark%20(95)-600x600.jpg","LuEkcc/4+dzvym/hMsfDcw==":"adobe%20spark%20(96)-600x600.jpg","lwS1Rq8JBbiwraXZJunoQA==":"adobe%20spark%20(97)-600x600.jpg","VfYao4PYtkj3+gBmEzLfDQ==":"adobe%20spark%20(99)-600x150.jpg","zqkEwKRSNJIRlMR5febxOw==":"adobe%20spark%20(98)-600x600.jpg","t61DW+7eUpPNGGX4hdn94A==":"adobe%20spark%20(81)-600x400.jpg","G52wH7zLJnSL/Gc+cIATBg==":"adobe%20spark%20(80)-600x400.jpg","3yPzTDlCYhbWWjrYyTtUHg==":"mapping2-2000x1324.jpg","fV1Bkbx7Wnca6G0hLWVvEA==":"17855081_1492536334147685_3154629460821478546_o-2000x1333.jpg","rPGXXfBdKIxjKF/BKB7yDA==":"computer&map-2000x1150.jpg","z5ytyWKFVVIqHAPhL5QSgQ==":"img_2446%20(2)-2000x682.jpg","oqWYHOVng7qvLN1tSlMZ3g==":"img_2441%20(2)-2000x691.jpg","3NG8selXuWKuOmhMASetww==":"img_2441%20(3)-2000x910.jpg","8SMi7ev2LXuKA7ZCRNvwUg==":"file_000(2)-2000x1500.png","INPV2LCGNTOqovtzltxATQ==":"capture321-1400x552.jpg","pOYEYOBySggZIMKKool+TQ==":"10974552_887041408030517_5057562095255386811_o-2000x1333.jpg","CxGrWPeFRqtznvZ5YmXoig==":"nkcppv-b88337940z-2000x1287.jpg","6ShkJJddE+ULMdp7eGaydg==":"j0185113-2000x1350.jpg","gLZIWT/c5/9e/dk3p61CkA==":"ph01957j-2000x1377.jpg","HlpA9HczaRJJt0vqQsev0g==":"j0185113%20(2)-2000x600.jpg","m6W4N7qm/cfdLxuXCOe9aw==":"mbr-3-2000x1333.jpg","59eK2B8Hr1UHv8GJLcLmrg==":"download-2000x397.jpg","Rt9X/83xaE/yj4V2G+YrXw==":"mbr-1-2000x1334.jpg","YLb9MnOP3cOmcCvABNeNcA==":"futuraflatwhite.svg","rNvAkEBZAOXFMAcqdh9ylg==":"mbr-2-2000x1334.jpg","E9iS7be+FM18AP9MDm+7pw==":"mbr-4-2000x1333.jpg","pSF2ZTbGdCozJNkU2VBvkw==":"17855081_1492536334147685_3154629460821478546_o-1-2000x1333.jpg","yOnjafpv67xbCMjxz2kYng==":"17758262_1492536397481012_8018865693756767061_o%20(2)-2000x1124.jpg","8YM5h33oKw2o779oZ/FVBw==":"img-2000x1125.png","RyBbCEV+z95pr96Lb8bgUA==":"mobile-workforce-680x365_c-1-2000x1073.jpg","RbgZi4+WS1mn3E4ZLWbd3A==":"ph01957j-1-2000x1377.jpg","b92GFWyrwAynI9PXsaJ/uA==":"download-1-2000x397.jpg","KsPF0VpWCCXUTgyPepu5mA==":"mbr-5-2000x1333.jpg"}